MANIFEST.in
PluginDisableAutoSave.py
README.rst
setup.cfg
setup.py
scribes.edit.disable_auto_save.egg-info/PKG-INFO
scribes.edit.disable_auto_save.egg-info/SOURCES.txt
scribes.edit.disable_auto_save.egg-info/dependency_links.txt
scribes.edit.disable_auto_save.egg-info/not-zip-safe
scribes.edit.disable_auto_save.egg-info/top_level.txt