Metadata-Version: 1.0
Name: scribes.edit.disable-auto-save
Version: 0.2.2
Summary: Scribes plugin. Disables default autosave on timer and editor focus loss
Home-page: http://github.com/baverman/scribes-goodies
Author: Anton Bobrov
Author-email: bobrov@vl.ru
License: UNKNOWN
Platform: UNKNOWN
